hns_console_logging/__init__.py
hns_console_logging-20.5.dist-info/LICENSE
hns_console_logging-20.5.dist-info/METADATA
hns_console_logging-20.5.dist-info/WHEEL
hns_console_logging-20.5.dist-info/top_level.txt
hns_console_logging-20.5.dist-info/RECORD
