Metadata-Version: 2.1
Name: hns-console-logging
Version: 20.5
Summary: Just a simple script to create a logger object for logging to console
Home-page: https://gitlab.com/horsebridge/hns_console_logging.git
Author: Nitin Sidhu
Author-email: nitin.sidhu23@gmail.com
License: MIT
Platform: UNKNOWN
Classifier: License :: OSI Approved :: MIT License
Classifier: Operating System :: OS Independent
Classifier: Programming Language :: Python :: 3.6
Classifier: Programming Language :: Python :: 3.7
Classifier: Programming Language :: Python :: 3.8
Requires-Python: ~=3.6
